ease_plot/__init__.py
ease_plot/class_cmaps.py
ease_plot/class_plot_map.py
ease_plot/getopts.py
ease_plot/map2d.py
ease_plot/version.py
gallery/__init__.py
statics/3gauss.pal
statics/3saw.pal
statics/Allura-Regular.ttf
statics/BkBlAqGrYeOrReViWh200.pal
statics/BlAqGrWh2YeOrReVi22.pal
statics/BlAqGrYeOrRe.pal
statics/BlAqGrYeOrReVi200.pal
statics/BlGrYeOrReVi200.pal
statics/BlRe.pal
statics/BlWhRe.pal
statics/BlueDarkOrange18.pal
statics/BlueDarkRed18.pal
statics/BlueGreen14.pal
statics/BlueRed.pal
statics/BlueRedGray.pal
statics/BlueWhiteOrangeRed.pal
statics/BlueYellowRed.pal
statics/BrownBlue12.pal
statics/CBR_coldhot.pal
statics/CBR_drywet.pal
statics/CBR_set3.pal
statics/CBR_wet.pal
statics/Cat12.pal
statics/GHRSST_anomaly.pal
statics/GMT_cool.pal
statics/GMT_copper.pal
statics/GMT_drywet.pal
statics/GMT_gebco.pal
statics/GMT_globe.pal
statics/GMT_gray.pal
statics/GMT_haxby.pal
statics/GMT_hot.pal
statics/GMT_jet.pal
statics/GMT_nighttime.pal
statics/GMT_no_green.pal
statics/GMT_ocean.pal
statics/GMT_paired.pal
statics/GMT_panoply.pal
statics/GMT_polar.pal
statics/GMT_red2green.pal
statics/GMT_relief.pal
statics/GMT_relief_oceanonly.pal
statics/GMT_seis.pal
statics/GMT_split.pal
statics/GMT_topo.pal
statics/GMT_wysiwyg.pal
statics/GMT_wysiwygcont.pal
statics/GSFC_landsat_udf_density.pal
statics/GrayWhiteGray.pal
statics/GreenMagenta16.pal
statics/GreenYellow.pal
statics/Helvetica.ttf
statics/MO_Blue-Red-greyed_minimum.pal
statics/MO_greyed70_middle_rev.pal
statics/MO_sla.pal
statics/MO_thalassa.pal
statics/MPL_Accent.pal
statics/MPL_Blues.pal
statics/MPL_BrBG.pal
statics/MPL_BuGn.pal
statics/MPL_BuPu.pal
statics/MPL_Dark2.pal
statics/MPL_GnBu.pal
statics/MPL_Greens.pal
statics/MPL_Greys.pal
statics/MPL_OrRd.pal
statics/MPL_Oranges.pal
statics/MPL_PRGn.pal
statics/MPL_Paired.pal
statics/MPL_Pastel1.pal
statics/MPL_Pastel2.pal
statics/MPL_PiYG.pal
statics/MPL_PuBu.pal
statics/MPL_PuBuGn.pal
statics/MPL_PuOr.pal
statics/MPL_PuRd.pal
statics/MPL_Purples.pal
ease_plot-0.0.5.dist-info/METADATA
ease_plot-0.0.5.dist-info/WHEEL
ease_plot-0.0.5.dist-info/entry_points.txt
ease_plot-0.0.5.dist-info/top_level.txt
ease_plot-0.0.5.dist-info/RECORD
